pycure-0.0.2.dist-info/top_level.txt
pycure-0.0.2.dist-info/RECORD
pycure-0.0.2.dist-info/entry_points.txt
pycure-0.0.2.dist-info/METADATA
pycure-0.0.2.dist-info/WHEEL
pycure-0.0.2.dist-info/pydist.json
pycure-0.0.2.dist-info/DESCRIPTION.rst
pycure/__init__.py
pycure/precure.py
pycure/girl.py
