Metadata-Version: 2.0
Name: pycure
Version: 0.0.2
Summary: All about Japanese battle heroine "Pretty Cure"
Home-page: https://github.com/drillbits/pycure
Author: Jiro Nejime
Author-email: neji@drillbits.jp
License: MIT License
Platform: UNKNOWN
Classifier: Development Status :: 3 - Alpha
Classifier: Intended Audience :: Developers
Classifier: License :: OSI Approved :: MIT License
Classifier: Programming Language :: Python
Classifier: Programming Language :: Python :: 3.3
Classifier: Topic :: Utilities
Provides-Extra: testing
Requires-Dist: testfixtures; extra == 'testing'
